actappliance/misc.py
actappliance/models.py
actappliance/__init__.py
actappliance/act_errors.py
actappliance/permissions.py
actappliance/appliance.py
actappliance/helpers.py
actappliance/connections/rest.py
actappliance/connections/aioconnection.py
actappliance/connections/__init__.py
actappliance/connections/connection.py
actappliance/connections/ssh.py
actappliance/connections/aiossh.py
actappliance/connections/aiorest.py
actappliance-0.8.2.dist-info/RECORD
actappliance-0.8.2.dist-info/metadata.json
actappliance-0.8.2.dist-info/WHEEL
actappliance-0.8.2.dist-info/DESCRIPTION.rst
actappliance-0.8.2.dist-info/top_level.txt
actappliance-0.8.2.dist-info/METADATA
