Metadata-Version: 2.0
Name: actappliance
Version: 0.8.2
Summary: An abstraction utility for actifio appliances
Home-page: https://github.com/Brian-Williams/actappliance
Author: Brian Williams
Author-email: briancmwilliams@gmail.com
License: UNKNOWN
Keywords: automation testing
Platform: UNKNOWN
Classifier: Development Status :: 3 - Alpha
Classifier: Intended Audience :: Developers
Classifier: Programming Language :: Python :: 3
Classifier: Programming Language :: Python :: 3.6
Requires-Dist: requests
Requires-Dist: paramiko
Requires-Dist: bitpermissions
Requires-Dist: asyncssh
Requires-Dist: aiohttp
Provides-Extra: test
Requires-Dist: pytest (>=2.9.0); extra == 'test'
Requires-Dist: flake8; extra == 'test'
Requires-Dist: tenacity; extra == 'test'
